LICENSE
README.md
setup.py
httpcat/__init__.py
httpcat/compat.py
httpcat/config.py
httpcat/main.py
httpcat/utils.py
httpcat/services/__init__.py
httpcat/services/storage/__init__.py
httpcat/services/storage/uploader.py
httpcatlab.egg-info/PKG-INFO
httpcatlab.egg-info/SOURCES.txt
httpcatlab.egg-info/dependency_links.txt
httpcatlab.egg-info/requires.txt
httpcatlab.egg-info/top_level.txt